j2p/__init__.py
j2p/cli.py
ju2py-0.1.0.dist-info/METADATA
ju2py-0.1.0.dist-info/WHEEL
ju2py-0.1.0.dist-info/entry_points.txt
ju2py-0.1.0.dist-info/top_level.txt
ju2py-0.1.0.dist-info/RECORD
